aioguest/__init__.py
aioguest/_impl.py
aioguest/_version.py
aioguest/py.typed
aioguest-0.1.0.dist-info/LICENSE
aioguest-0.1.0.dist-info/LICENSE.APACHE2
aioguest-0.1.0.dist-info/LICENSE.MIT
aioguest-0.1.0.dist-info/METADATA
aioguest-0.1.0.dist-info/WHEEL
aioguest-0.1.0.dist-info/top_level.txt
aioguest-0.1.0.dist-info/RECORD
