Metadata-Version: 2.1
Name: aioguest
Version: 0.1.0
Summary: Run asyncio and another event loop in the same thread
Home-page: https://github.com/oremanj/aioguest
Author: Joshua Oreman
Author-email: oremanj@gmail.com
License: MIT -or- Apache License 2.0
Keywords: async,trio,asyncio
Classifier: License :: OSI Approved :: MIT License
Classifier: License :: OSI Approved :: Apache Software License
Classifier: Operating System :: POSIX :: Linux
Classifier: Operating System :: MacOS :: MacOS X
Classifier: Operating System :: Microsoft :: Windows
Classifier: Programming Language :: Python :: 3 :: Only
Classifier: Programming Language :: Python :: Implementation :: CPython
Classifier: Programming Language :: Python :: Implementation :: PyPy
Classifier: Development Status :: 2 - Pre-Alpha
Classifier: Intended Audience :: Developers
Requires-Python: >=3.7
License-File: LICENSE
License-File: LICENSE.APACHE2
License-File: LICENSE.MIT
Requires-Dist: attrs (>=21.3.0)
Requires-Dist: greenlet
Requires-Dist: trio (>=0.16.0)
Requires-Dist: sniffio (>=1.3.0)
Requires-Dist: outcome
